jt_phd_utils/maic_birra_bench_sims.py
jt_phd_utils-0.1.2.dist-info/METADATA
jt_phd_utils-0.1.2.dist-info/WHEEL
jt_phd_utils-0.1.2.dist-info/top_level.txt
jt_phd_utils-0.1.2.dist-info/RECORD
