Metadata-Version: 2.4
Name: jt-phd-utils
Version: 0.1.2
Summary: Assorted helper functions for my PhD, not generaly useful enough for their own packages.
Requires-Python: >=3.11
Requires-Dist: ma-utils==0.0.3
Requires-Dist: dantArrays==0.0.4
Requires-Dist: birra==0.1.1
Requires-Dist: pymaic==0.2
